pynance/__init__.py
pynance/myfunctions.py
test/__init__.py
test/test_myfunctions.py
pynance_tools-0.1.0.dist-info/LICENSE
pynance_tools-0.1.0.dist-info/METADATA
pynance_tools-0.1.0.dist-info/WHEEL
pynance_tools-0.1.0.dist-info/top_level.txt
pynance_tools-0.1.0.dist-info/RECORD
