Metadata-Version: 2.1
Name: pynance-tools
Version: 0.1.0
Summary: A Python library for financial calculations and formulas of TVM, and asset valuation.
Home-page: https://github.com/ricky122-5/pynance
Author: Rithvik Reddygari
Author-email: reddygari.rithvik@gmail.com
Classifier: Programming Language :: Python :: 3
Classifier: License :: OSI Approved :: MIT License
Classifier: Operating System :: OS Independent
Requires-Python: >=3.6
License-File: LICENSE
Requires-Dist: numpy
Requires-Dist: scipy
